jqqb_evaluator/__init__.py
jqqb_evaluator/evaluator.py
jqqb_evaluator/operators.py
jqqb_evaluator/rule.py
jqqb_evaluator/rule_group.py
jqqb_evaluator/test.py
jqqb_evaluator-0.0.1.dist-info/LICENSE
jqqb_evaluator-0.0.1.dist-info/METADATA
jqqb_evaluator-0.0.1.dist-info/WHEEL
jqqb_evaluator-0.0.1.dist-info/top_level.txt
jqqb_evaluator-0.0.1.dist-info/RECORD
