Metadata-Version: 2.1
Name: jqqb-evaluator
Version: 0.0.1
Summary: Python evaluator for jQuery-QueryBuilder rules
Home-page: https://github.com/shunyeka/jQuery-QueryBuilder-Python-Evaluator
Author: Amit Chotaliya
Author-email: amit@shunyeka.com
License: UNKNOWN
Platform: UNKNOWN
Classifier: Programming Language :: Python :: 3
Classifier: License :: OSI Approved :: MIT License
Classifier: Operating System :: OS Independent
Requires-Python: >=3.6
Requires-Dist: pytimeparse (~=1.1.8)
